divbase_lib/__init__.py
divbase_lib/exceptions.py
divbase_lib/s3_checksums.py
divbase_lib/api_schemas/__init__.py
divbase_lib/api_schemas/auth.py
divbase_lib/api_schemas/project_versions.py
divbase_lib/api_schemas/queries.py
divbase_lib/api_schemas/s3.py
divbase_lib/api_schemas/task_history.py
divbase_lib/api_schemas/vcf_dimensions.py
divbase_lib-0.1.0.dev2.dist-info/METADATA
divbase_lib-0.1.0.dev2.dist-info/WHEEL
divbase_lib-0.1.0.dev2.dist-info/RECORD
