Metadata-Version: 2.4
Name: divbase-lib
Version: 0.1.0.dev2
Summary: Library module for Divbase
Project-URL: Homepage, https://divbase.scilifelab.se
Project-URL: Documentation, https://scilifelabdatacentre.github.io/divbase
Project-URL: Repository, https://github.com/ScilifelabDataCentre/divbase
Project-URL: Issues, https://github.com/ScilifelabDataCentre/divbase/issues
Author-email: SciLifeLab Data Centre <datacentre@scilifelab.se>
License-Expression: MIT
Classifier: Development Status :: 3 - Alpha
Classifier: Environment :: Console
Classifier: Intended Audience :: Science/Research
Classifier: License :: OSI Approved :: MIT License
Classifier: Operating System :: OS Independent
Classifier: Programming Language :: Python :: 3
Classifier: Programming Language :: Python :: 3.12
Classifier: Programming Language :: Python :: 3.13
Classifier: Programming Language :: Python :: 3.14
Requires-Python: >=3.12
Requires-Dist: boto3<2,>=1.42.27
Requires-Dist: pandas<3,>=2.3.3
Requires-Dist: pydantic<3,>=2.12.5
Requires-Dist: pyyaml<7,>=6.0.3
